sca3300.py
sca3300-1.0.1.dist-info/LICENSE
sca3300-1.0.1.dist-info/METADATA
sca3300-1.0.1.dist-info/WHEEL
sca3300-1.0.1.dist-info/top_level.txt
sca3300-1.0.1.dist-info/RECORD
