Metadata-Version: 2.1
Name: sca3300
Version: 1.0.1
Summary: SCA3300 Linux driver with dependency on just spidev
Home-page: https://github.com/algebratech/sca3300-driver
Author: Algebra Global, Inc
License: MIT
Keywords: sca3300 raspberry pi acceleration spi device hardware
Platform: UNKNOWN
Classifier: Development Status :: 3 - Alpha
Classifier: Intended Audience :: Developers
Classifier: Topic :: Software Development :: Libraries
Classifier: Topic :: System :: Hardware
Classifier: License :: OSI Approved :: MIT License
Classifier: Programming Language :: Python :: 3
Classifier: Programming Language :: Python :: 3.4
Classifier: Programming Language :: Python :: 3.5
Requires-Python: >3.4.0
